datarecipe/__init__.py
datarecipe/common_tools.py
datarecipe/examine.py
datarecipe/mysql.py
datarecipe/s3_api.py
datarecipe-2.1.1.dist-info/LICENSE.txt
datarecipe-2.1.1.dist-info/METADATA
datarecipe-2.1.1.dist-info/WHEEL
datarecipe-2.1.1.dist-info/top_level.txt
datarecipe-2.1.1.dist-info/RECORD
