Metadata-Version: 2.1
Name: datarecipe
Version: 2.1.1
Summary: A recipe for every data baker
Home-page: https://github.com/Adward-Chen/databaker/tree/main
Author: Hanfan Chen
Author-email: HanfanC@outlook.com
Classifier: Programming Language :: Python :: 3.10
Classifier: License :: OSI Approved :: MIT License
Classifier: Operating System :: OS Independent
License-File: LICENSE.txt
